[{"object": "card", "id": "219210d3-263c-41c4-9211-0e59b2d4ccf3", "oracle_id": "6ad8011d-3471-4369-9d68-b264cc027487", "multiverse_ids": [], "tcgplayer_id": 591107, "cardmarket_id": 796501, "name": "Sol Ring", "lang": "en", "released_at": "2024-11-15", "uri": "https://api.scryfall.com/cards/219210d3-263c-41c4-9211-0e59b2d4ccf3", "scryfall_uri": "https://scryfall.com/card/fdc/2/sol-ring?utm_source=api", "layout": "normal", "highres_image": true, "image_status": "highres_scan", "image_uris": {"small": "https://cards.scryfall.io/small/front/2/1/219210d3-263c-41c4-9211-0e59b2d4ccf3.jpg?1766989024", "normal": "https://cards.scryfall.io/normal/front/2/1/219210d3-263c-41c4-9211-0e59b2d4ccf3.jpg?1766989024", "large": "https://cards.scryfall.io/large/front/2/1/219210d3-263c-41c4-9211-0e59b2d4ccf3.jpg?1766989024", "png": "https://cards.scryfall.io/png/front/2/1/219210d3-263c-41c4-9211-0e59b2d4ccf3.png?1766989024", "art_crop": "https://cards.scryfall.io/art_crop/front/2/1/219210d3-263c-41c4-9211-0e59b2d4ccf3.jpg?1766989024", "border_crop": "https://cards.scryfall.io/border_crop/front/2/1/219210d3-263c-41c4-9211-0e59b2d4ccf3.jpg?1766989024"}, "mana_cost": "{1}", "cmc": 1.0, "type_line": "Artifact", "oracle_text": "{T}: Add {C}{C}.", "colors": [], "color_identity": [], "keywords": [], "produced_mana": ["C"], "legalities": {"standard": "not_legal", "future": "not_legal", "historic": "not_legal", "timeless": "not_legal", "gladiator": "not_legal", "pioneer": "not_legal", "modern": "not_legal", "legacy": "banned", "pauper": "not_legal", "vintage": "restricted", "penny": "not_legal", "commander": "legal", "oathbreaker": "banned", "standardbrawl": "not_legal", "brawl": "not_legal", "alchemy": "not_legal", "paupercommander": "not_legal", "duel": "banned", "oldschool": "not_legal", "premodern": "not_legal", "predh": "legal"}, "games": ["paper"], "reserved": false, "game_changer": false, "foil": true, "nonfoil": false, "finishes": ["foil"], "oversized": false, "promo": false, "reprint": true, "variation": false, "set_id": "2a0b24ac-7614-4a08-b58a-b64f7c173361", "set": "fdc", "set_name": "Foundations Commander", "set_type": "commander", "set_uri": "https://api.scryfall.com/sets/2a0b24ac-7614-4a08-b58a-b64f7c173361", "set_search_uri": "https://api.scryfall.com/cards/search?order=set&q=e%3Afdc&unique=prints", "scryfall_set_uri": "https://scryfall.com/sets/fdc?utm_source=api", "rulings_uri": "https://api.scryfall.com/cards/219210d3-263c-41c4-9211-0e59b2d4ccf3/rulings", "prints_search_uri": "https://api.scryfall.com/cards/search?order=released&q=oracleid%3A6ad8011d-3471-4369-9d68-b264cc027487&unique=prints", "collector_number": "2", "digital": false, "rarity": "uncommon", "flavor_text": "Lost to time is the artificer's art of trapping light from a distant star in a ring of purest gold.", "card_back_id": "0aeebaf5-8c7d-4636-9e82-8c27447861f7", "artist": "Mike Bierek", "artist_ids": ["e5f52ef5-1a2e-4128-90b0-ccc71cd47ea7"], "illustration_id": "146aaae4-93f4-409a-be32-010e86d137da", "border_color": "black", "frame": "2015", "full_art": false, "textless": false, "booster": false, "story_spotlight": false, "promo_types": ["startercollection"], "edhrec_rank": 1, "preview": {"source": "Wizards of the Coast", "source_uri": "", "previewed_at": "2024-10-29"}, "prices": {"usd": null, "usd_foil": "1.56", "usd_etched": null, "eur": null, "eur_foil": "1.75", "tix": null}, "related_uris": {"tcgplayer_infinite_articles": "https://partner.tcgplayer.com/c/4931599/1830156/21018?subId1=api&trafcat=tcgplayer.com%2Fsearch%2Farticles&u=https%3A%2F%2Fwww.tcgplayer.com%2Fsearch%2Farticles%3FproductLineName%3Dmagic%26q%3DSol%2BRing", "tcgplayer_infinite_decks": "https://partner.tcgplayer.com/c/4931599/1830156/21018?subId1=api&trafcat=tcgplayer.com%2Fsearch%2Fdecks&u=https%3A%2F%2Fwww.tcgplayer.com%2Fsearch%2Fdecks%3FproductLineName%3Dmagic%26q%3DSol%2BRing", "edhrec": "https://edhrec.com/route/?cc=Sol+Ring"}, "purchase_uris": {"tcgplayer": "https://partner.tcgplayer.com/c/4931599/1830156/21018?subId1=api&u=https%3A%2F%2Fwww.tcgplayer.com%2Fproduct%2F591107%3Fpage%3D1", "cardmarket": "https://www.cardmarket.com/en/Magic/Products?idProduct=796501&referrer=scryfall&utm_campaign=card_prices&utm_medium=text&utm_source=scryfall", "cardhoarder": "https://www.cardhoarder.com/cards?affiliate_id=scryfall&data%5Bsearch%5D=Sol+Ring&ref=card-profile&utm_campaign=affiliate&utm_medium=card&utm_source=scryfall"}}, {"object": "card", "id": "667b6c3b-75cc-4adf-b205-80925ca76d2a", "oracle_id": "0895c9b7-ae7d-4bb3-af17-3b75deb50a25", "multiverse_ids": [], "tcgplayer_id": 591108, "cardmarket_id": 796502, "name": "Command Tower", "lang": "en", "released_at": "2024-11-15", "uri": "https://api.scryfall.com/cards/667b6c3b-75cc-4adf-b205-80925ca76d2a", "scryfall_uri": "https://scryfall.com/card/fdc/3/command-tower?utm_source=api", "layout": "normal", "highres_image": true, "image_status": "highres_scan", "image_uris": {"small": "https://cards.scryfall.io/small/front/6/6/667b6c3b-75cc-4adf-b205-80925ca76d2a.jpg?1766989009", "normal": "https://cards.scryfall.io/normal/front/6/6/667b6c3b-75cc-4adf-b205-80925ca76d2a.jpg?1766989009", "large": "https://cards.scryfall.io/large/front/6/6/667b6c3b-75cc-4adf-b205-80925ca76d2a.jpg?1766989009", "png": "https://cards.scryfall.io/png/front/6/6/667b6c3b-75cc-4adf-b205-80925ca76d2a.png?1766989009", "art_crop": "https://cards.scryfall.io/art_crop/front/6/6/667b6c3b-75cc-4adf-b205-80925ca76d2a.jpg?1766989009", "border_crop": "https://cards.scryfall.io/border_crop/front/6/6/667b6c3b-75cc-4adf-b205-80925ca76d2a.jpg?1766989009"}, "mana_cost": "", "cmc": 0.0, "type_line": "Land", "oracle_text": "{T}: Add one mana of any color in your commander's color identity.", "colors": [], "color_identity": [], "keywords": [], "produced_mana": ["B", "G", "R", "U", "W"], "all_parts": [{"object": "related_card", "id": "667b6c3b-75cc-4adf-b205-80925ca76d2a", "component": "combo_piece", "name": "Command Tower", "type_line": "Land", "uri": "https://api.scryfall.com/cards/667b6c3b-75cc-4adf-b205-80925ca76d2a"}, {"object": "related_card", "id": "ad03209f-568a-40f5-8470-a083080e6831", "component": "combo_piece", "name": "Tower Winder", "type_line": "Creature \u2014 Snake", "uri": "https://api.scryfall.com/cards/ad03209f-568a-40f5-8470-a083080e6831"}], "legalities": {"standard": "not_legal", "future": "not_legal", "historic": "legal", "timeless": "legal", "gladiator": "legal", "pioneer": "legal", "modern": "legal", "legacy": "legal", "pauper": "legal", "vintage": "legal", "penny": "not_legal", "commander": "legal", "oathbreaker": "legal", "standardbrawl": "legal", "brawl": "legal", "alchemy": "not_legal", "paupercommander": "legal", "duel": "legal", "oldschool": "not_legal", "premodern": "not_legal", "predh": "not_legal"}, "games": ["paper"], "reserved": false, "game_changer": false, "foil": true, "nonfoil": false, "finishes": ["foil"], "oversized": false, "promo": false, "reprint": true, "variation": false, "set_id": "2a0b24ac-7614-4a08-b58a-b64f7c173361", "set": "fdc", "set_name": "Foundations Commander", "set_type": "commander", "set_uri": "https://api.scryfall.com/sets/2a0b24ac-7614-4a08-b58a-b64f7c173361", "set_search_uri": "https://api.scryfall.com/cards/search?order=set&q=e%3Afdc&unique=prints", "scryfall_set_uri": "https://scryfall.com/sets/fdc?utm_source=api", "rulings_uri": "https://api.scryfall.com/cards/667b6c3b-75cc-4adf-b205-80925ca76d2a/rulings", "prints_search_uri": "https://api.scryfall.com/cards/search?order=released&q=oracleid%3A0895c9b7-ae7d-4bb3-af17-3b75deb50a25&unique=prints", "collector_number": "3", "digital": false, "rarity": "common", "flavor_text": "When defeat is near and guidance is scarce, all eyes look in one direction.", "card_back_id": "0aeebaf5-8c7d-4636-9e82-8c27447861f7", "artist": "Ryan Yee", "artist_ids": ["8955dca7-3e37-42b4-83a9-167c78a2178f"], "illustration_id": "8218c3fe-62e3-4639-a305-68897194c3d3", "border_color": "black", "frame": "2015", "full_art": false, "textless": false, "booster": false, "story_spotlight": false, "promo_types": ["startercollection"], "edhrec_rank": 2, "preview": {"source": "Wizards of the Coast", "source_uri": "", "previewed_at": "2024-10-29"}, "prices": {"usd": null, "usd_foil": "0.42", "usd_etched": null, "eur": null, "eur_foil": "0.77", "tix": null}, "related_uris": {"tcgplayer_infinite_articles": "https://partner.tcgplayer.com/c/4931599/1830156/21018?subId1=api&trafcat=tcgplayer.com%2Fsearch%2Farticles&u=https%3A%2F%2Fwww.tcgplayer.com%2Fsearch%2Farticles%3FproductLineName%3Dmagic%26q%3DCommand%2BTower", "tcgplayer_infinite_decks": "https://partner.tcgplayer.com/c/4931599/1830156/21018?subId1=api&trafcat=tcgplayer.com%2Fsearch%2Fdecks&u=https%3A%2F%2Fwww.tcgplayer.com%2Fsearch%2Fdecks%3FproductLineName%3Dmagic%26q%3DCommand%2BTower", "edhrec": "https://edhrec.com/route/?cc=Command+Tower"}, "purchase_uris": {"tcgplayer": "https://partner.tcgplayer.com/c/4931599/1830156/21018?subId1=api&u=https%3A%2F%2Fwww.tcgplayer.com%2Fproduct%2F591108%3Fpage%3D1", "cardmarket": "https://www.cardmarket.com/en/Magic/Products?idProduct=796502&referrer=scryfall&utm_campaign=card_prices&utm_medium=text&utm_source=scryfall", "cardhoarder": "https://www.cardhoarder.com/cards?affiliate_id=scryfall&data%5Bsearch%5D=Command+Tower&ref=card-profile&utm_campaign=affiliate&utm_medium=card&utm_source=scryfall"}}, {"object": "card", "id": "7b4b3e1c-1dc4-46d9-9234-f9d1d2ebb8f8", "oracle_id": "0bc7f093-bef0-4f1a-852c-4b75ebf54838", "multiverse_ids": [], "tcgplayer_id": 591105, "cardmarket_id": 796500, "name": "Arcane Signet", "lang": "en", "released_at": "2024-11-15", "uri": "https://api.scryfall.com/cards/7b4b3e1c-1dc4-46d9-9234-f9d1d2ebb8f8", "scryfall_uri": "https://scryfall.com/card/fdc/1/arcane-signet?utm_source=api", "layout": "normal", "highres_image": true, "image_status": "highres_scan", "image_uris": {"small": "https://cards.scryfall.io/small/front/7/b/7b4b3e1c-1dc4-46d9-9234-f9d1d2ebb8f8.jpg?1766988964", "normal": "https://cards.scryfall.io/normal/front/7/b/7b4b3e1c-1dc4-46d9-9234-f9d1d2ebb8f8.jpg?1766988964", "large": "https://cards.scryfall.io/large/front/7/b/7b4b3e1c-1dc4-46d9-9234-f9d1d2ebb8f8.jpg?1766988964", "png": "https://cards.scryfall.io/png/front/7/b/7b4b3e1c-1dc4-46d9-9234-f9d1d2ebb8f8.png?1766988964", "art_crop": "https://cards.scryfall.io/art_crop/front/7/b/7b4b3e1c-1dc4-46d9-9234-f9d1d2ebb8f8.jpg?1766988964", "border_crop": "https://cards.scryfall.io/border_crop/front/7/b/7b4b3e1c-1dc4-46d9-9234-f9d1d2ebb8f8.jpg?1766988964"}, "mana_cost": "{2}", "cmc": 2.0, "type_line": "Artifact", "oracle_text": "{T}: Add one mana of any color in your commander's color identity.", "colors": [], "color_identity": [], "keywords": [], "produced_mana": ["B", "G", "R", "U", "W"], "legalities": {"standard": "not_legal", "future": "not_legal", "historic": "legal", "timeless": "legal", "gladiator": "legal", "pioneer": "legal", "modern": "legal", "legacy": "legal", "pauper": "legal", "vintage": "legal", "penny": "not_legal", "commander": "legal", "oathbreaker": "legal", "standardbrawl": "legal", "brawl": "legal", "alchemy": "not_legal", "paupercommander": "legal", "duel": "legal", "oldschool": "not_legal", "premodern": "not_legal", "predh": "not_legal"}, "games": ["paper"], "reserved": false, "game_changer": false, "foil": true, "nonfoil": false, "finishes": ["foil"], "oversized": false, "promo": false, "reprint": true, "variation": false, "set_id": "2a0b24ac-7614-4a08-b58a-b64f7c173361", "set": "fdc", "set_name": "Foundations Commander", "set_type": "commander", "set_uri": "https://api.scryfall.com/sets/2a0b24ac-7614-4a08-b58a-b64f7c173361", "set_search_uri": "https://api.scryfall.com/cards/search?order=set&q=e%3Afdc&unique=prints", "scryfall_set_uri": "https://scryfall.com/sets/fdc?utm_source=api", "rulings_uri": "https://api.scryfall.com/cards/7b4b3e1c-1dc4-46d9-9234-f9d1d2ebb8f8/rulings", "prints_search_uri": "https://api.scryfall.com/cards/search?order=released&q=oracleid%3A0bc7f093-bef0-4f1a-852c-4b75ebf54838&unique=prints", "collector_number": "1", "digital": false, "rarity": "uncommon", "flavor_text": "It started as a mere drop of water. The Magic Mirror crystallized it into much more.", "card_back_id": "0aeebaf5-8c7d-4636-9e82-8c27447861f7", "artist": "Dan Murayama Scott", "artist_ids": ["f852fa13-137e-40f2-bbc1-0f01df09c0e0"], "illustration_id": "06d7b990-021a-4b1f-9333-4fc82adf0ea4", "border_color": "black", "frame": "2015", "full_art": false, "textless": false, "booster": false, "story_spotlight": false, "promo_types": ["startercollection"], "edhrec_rank": 3, "preview": {"source": "Wizards of the Coast", "source_uri": "", "previewed_at": "2024-10-29"}, "prices": {"usd": null, "usd_foil": "0.57", "usd_etched": null, "eur": null, "eur_foil": "1.28", "tix": null}, "related_uris": {"tcgplayer_infinite_articles": "https://partner.tcgplayer.com/c/4931599/1830156/21018?subId1=api&trafcat=tcgplayer.com%2Fsearch%2Farticles&u=https%3A%2F%2Fwww.tcgplayer.com%2Fsearch%2Farticles%3FproductLineName%3Dmagic%26q%3DArcane%2BSignet", "tcgplayer_infinite_decks": "https://partner.tcgplayer.com/c/4931599/1830156/21018?subId1=api&trafcat=tcgplayer.com%2Fsearch%2Fdecks&u=https%3A%2F%2Fwww.tcgplayer.com%2Fsearch%2Fdecks%3FproductLineName%3Dmagic%26q%3DArcane%2BSignet", "edhrec": "https://edhrec.com/route/?cc=Arcane+Signet"}, "purchase_uris": {"tcgplayer": "https://partner.tcgplayer.com/c/4931599/1830156/21018?subId1=api&u=https%3A%2F%2Fwww.tcgplayer.com%2Fproduct%2F591105%3Fpage%3D1", "cardmarket": "https://www.cardmarket.com/en/Magic/Products?idProduct=796500&referrer=scryfall&utm_campaign=card_prices&utm_medium=text&utm_source=scryfall", "cardhoarder": "https://www.cardhoarder.com/cards?affiliate_id=scryfall&data%5Bsearch%5D=Arcane+Signet&ref=card-profile&utm_campaign=affiliate&utm_medium=card&utm_source=scryfall"}}]