[{"object": "card", "id": "187cf6d5-c352-48f2-b8bf-fe1bf946e2ac", "oracle_id": "bf690282-125f-431c-a363-39f6772324c8", "multiverse_ids": [], "tcgplayer_id": 78626, "name": "Myr", "lang": "en", "released_at": "2004-01-01", "uri": "https://api.scryfall.com/cards/187cf6d5-c352-48f2-b8bf-fe1bf946e2ac", "scryfall_uri": "https://scryfall.com/card/p04/4/myr?utm_source=api", "layout": "token", "highres_image": true, "image_status": "highres_scan", "image_uris": {"small": "https://cards.scryfall.io/small/front/1/8/187cf6d5-c352-48f2-b8bf-fe1bf946e2ac.jpg?1561756726", "normal": "https://cards.scryfall.io/normal/front/1/8/187cf6d5-c352-48f2-b8bf-fe1bf946e2ac.jpg?1561756726", "large": "https://cards.scryfall.io/large/front/1/8/187cf6d5-c352-48f2-b8bf-fe1bf946e2ac.jpg?1561756726", "png": "https://cards.scryfall.io/png/front/1/8/187cf6d5-c352-48f2-b8bf-fe1bf946e2ac.png?1561756726", "art_crop": "https://cards.scryfall.io/art_crop/front/1/8/187cf6d5-c352-48f2-b8bf-fe1bf946e2ac.jpg?1561756726", "border_crop": "https://cards.scryfall.io/border_crop/front/1/8/187cf6d5-c352-48f2-b8bf-fe1bf946e2ac.jpg?1561756726"}, "mana_cost": "", "cmc": 0.0, "type_line": "Token Artifact Creature \u2014 Myr", "oracle_text": "", "power": "1", "toughness": "1", "colors": [], "color_identity": [], "keywords": [], "all_parts": [{"object": "related_card", "id": "923c3656-5cdd-4be8-a158-5d5801f8e382", "component": "combo_piece", "name": "Genesis Chamber", "type_line": "Artifact", "uri": "https://api.scryfall.com/cards/923c3656-5cdd-4be8-a158-5d5801f8e382"}, {"object": "related_card", "id": "91e7faa4-160e-47d9-a9a1-5928d9d2b5e4", "component": "combo_piece", "name": "Origin Spellbomb", "type_line": "Artifact", "uri": "https://api.scryfall.com/cards/91e7faa4-160e-47d9-a9a1-5928d9d2b5e4"}, {"object": "related_card", "id": "4a1af62e-d566-4f39-a467-244602c9240b", "component": "combo_piece", "name": "Myr Matrix", "type_line": "Artifact", "uri": "https://api.scryfall.com/cards/4a1af62e-d566-4f39-a467-244602c9240b"}, {"object": "related_card", "id": "79afcfb3-7483-491c-87df-f8ce01c37eb0", "component": "combo_piece", "name": "Urtet, Remnant of Memnarch", "type_line": "Legendary Artifact Creature \u2014 Myr", "uri": "https://api.scryfall.com/cards/79afcfb3-7483-491c-87df-f8ce01c37eb0"}, {"object": "related_card", "id": "edf98768-c7dd-434e-8883-19b47ad45790", "component": "combo_piece", "name": "Mirrodin Besieged", "type_line": "Enchantment", "uri": "https://api.scryfall.com/cards/edf98768-c7dd-434e-8883-19b47ad45790"}, {"object": "related_card", "id": "78ea3e84-2d78-489f-875a-48e58c956451", "component": "combo_piece", "name": "Myrsmith", "type_line": "Creature \u2014 Human Artificer", "uri": "https://api.scryfall.com/cards/78ea3e84-2d78-489f-875a-48e58c956451"}, {"object": "related_card", "id": "71a76840-47f7-4e1e-b68b-00cb7da98cdf", "component": "combo_piece", "name": "Myr Turbine", "type_line": "Artifact", "uri": "https://api.scryfall.com/cards/71a76840-47f7-4e1e-b68b-00cb7da98cdf"}, {"object": "related_card", "id": "187cf6d5-c352-48f2-b8bf-fe1bf946e2ac", "component": "token", "name": "Myr", "type_line": "Token Artifact Creature \u2014 Myr", "uri": "https://api.scryfall.com/cards/187cf6d5-c352-48f2-b8bf-fe1bf946e2ac"}, {"object": "related_card", "id": "0db4cf09-8cf0-4aa7-8bfe-fe600352032d", "component": "combo_piece", "name": "Myr Battlesphere", "type_line": "Artifact Creature \u2014 Myr Construct", "uri": "https://api.scryfall.com/cards/0db4cf09-8cf0-4aa7-8bfe-fe600352032d"}, {"object": "related_card", "id": "18957d46-01e9-4ef0-97ba-ddbe5b34ea10", "component": "combo_piece", "name": "Myr Incubator", "type_line": "Artifact", "uri": "https://api.scryfall.com/cards/18957d46-01e9-4ef0-97ba-ddbe5b34ea10"}, {"object": "related_card", "id": "878a0e52-910a-45eb-9472-866fba890731", "component": "combo_piece", "name": "Master's Call", "type_line": "Instant", "uri": "https://api.scryfall.com/cards/878a0e52-910a-45eb-9472-866fba890731"}], "legalities": {"standard": "not_legal", "future": "not_legal", "historic": "not_legal", "timeless": "not_legal", "gladiator": "not_legal", "pioneer": "not_legal", "modern": "not_legal", "legacy": "not_legal", "pauper": "not_legal", "vintage": "not_legal", "penny": "not_legal", "commander": "not_legal", "oathbreaker": "not_legal", "standardbrawl": "not_legal", "brawl": "not_legal", "alchemy": "not_legal", "paupercommander": "not_legal", "duel": "not_legal", "oldschool": "not_legal", "premodern": "not_legal", "predh": "not_legal"}, "games": ["paper"], "reserved": false, "game_changer": false, "foil": false, "nonfoil": true, "finishes": ["nonfoil"], "oversized": false, "promo": true, "reprint": true, "variation": false, "set_id": "5ba81c6d-2344-4760-bb13-b7276205e73e", "set": "p04", "set_name": "Magic Player Rewards 2004", "set_type": "promo", "set_uri": "https://api.scryfall.com/sets/5ba81c6d-2344-4760-bb13-b7276205e73e", "set_search_uri": "https://api.scryfall.com/cards/search?order=set&q=e%3Ap04&unique=prints", "scryfall_set_uri": "https://scryfall.com/sets/p04?utm_source=api", "rulings_uri": "https://api.scryfall.com/cards/187cf6d5-c352-48f2-b8bf-fe1bf946e2ac/rulings", "prints_search_uri": "https://api.scryfall.com/cards/search?order=released&q=oracleid%3Abf690282-125f-431c-a363-39f6772324c8&unique=prints", "collector_number": "4", "digital": false, "rarity": "common", "card_back_id": "0aeebaf5-8c7d-4636-9e82-8c27447861f7", "artist": "Wayne England", "artist_ids": ["62dc90c0-4bc2-4d42-ad76-59cad9243566"], "illustration_id": "b4482da5-2b7a-44d0-8446-fb0ea007adf3", "border_color": "black", "frame": "2003", "full_art": false, "textless": false, "booster": false, "story_spotlight": false, "promo_types": ["playerrewards"], "prices": {"usd": "10.52", "usd_foil": null, "usd_etched": null, "eur": null, "eur_foil": null, "tix": null}, "related_uris": {"tcgplayer_infinite_articles": "https://partner.tcgplayer.com/c/4931599/1830156/21018?subId1=api&trafcat=tcgplayer.com%2Fsearch%2Farticles&u=https%3A%2F%2Fwww.tcgplayer.com%2Fsearch%2Farticles%3FproductLineName%3Dmagic%26q%3DMyr", "tcgplayer_infinite_decks": "https://partner.tcgplayer.com/c/4931599/1830156/21018?subId1=api&trafcat=tcgplayer.com%2Fsearch%2Fdecks&u=https%3A%2F%2Fwww.tcgplayer.com%2Fsearch%2Fdecks%3FproductLineName%3Dmagic%26q%3DMyr", "edhrec": "https://edhrec.com/route/?cc=Myr"}, "purchase_uris": {"tcgplayer": "https://partner.tcgplayer.com/c/4931599/1830156/21018?subId1=api&u=https%3A%2F%2Fwww.tcgplayer.com%2Fproduct%2F78626%3Fpage%3D1", "cardmarket": "https://www.cardmarket.com/en/Magic/Products/Search?referrer=scryfall&searchString=Myr&utm_campaign=card_prices&utm_medium=text&utm_source=scryfall", "cardhoarder": "https://www.cardhoarder.com/cards?affiliate_id=scryfall&data%5Bsearch%5D=Myr&ref=card-profile&utm_campaign=affiliate&utm_medium=card&utm_source=scryfall"}}, {"object": "card", "id": "2b77caf8-711b-4597-a5a5-dead81568e5b", "oracle_id": "ca1144c2-49a3-49b4-9085-3094141769ea", "multiverse_ids": [], "tcgplayer_id": 38328, "cardmarket_id": 17567, "name": "Powder Keg", "lang": "en", "released_at": "2004-01-01", "uri": "https://api.scryfall.com/cards/2b77caf8-711b-4597-a5a5-dead81568e5b", "scryfall_uri": "https://scryfall.com/card/p04/1/powder-keg?utm_source=api", "layout": "normal", "highres_image": true, "image_status": "highres_scan", "image_uris": {"small": "https://cards.scryfall.io/small/front/2/b/2b77caf8-711b-4597-a5a5-dead81568e5b.jpg?1561756834", "normal": "https://cards.scryfall.io/normal/front/2/b/2b77caf8-711b-4597-a5a5-dead81568e5b.jpg?1561756834", "large": "https://cards.scryfall.io/large/front/2/b/2b77caf8-711b-4597-a5a5-dead81568e5b.jpg?1561756834", "png": "https://cards.scryfall.io/png/front/2/b/2b77caf8-711b-4597-a5a5-dead81568e5b.png?1561756834", "art_crop": "https://cards.scryfall.io/art_crop/front/2/b/2b77caf8-711b-4597-a5a5-dead81568e5b.jpg?1561756834", "border_crop": "https://cards.scryfall.io/border_crop/front/2/b/2b77caf8-711b-4597-a5a5-dead81568e5b.jpg?1561756834"}, "mana_cost": "{2}", "cmc": 2.0, "type_line": "Artifact", "oracle_text": "At the beginning of your upkeep, you may put a fuse counter on this artifact.\n{T}, Sacrifice this artifact: Destroy each artifact and creature with mana value equal to the number of fuse counters on this artifact.", "colors": [], "color_identity": [], "keywords": [], "legalities": {"standard": "not_legal", "future": "not_legal", "historic": "not_legal", "timeless": "not_legal", "gladiator": "not_legal", "pioneer": "not_legal", "modern": "not_legal", "legacy": "legal", "pauper": "not_legal", "vintage": "legal", "penny": "not_legal", "commander": "legal", "oathbreaker": "legal", "standardbrawl": "not_legal", "brawl": "not_legal", "alchemy": "not_legal", "paupercommander": "not_legal", "duel": "legal", "oldschool": "not_legal", "premodern": "legal", "predh": "legal"}, "games": ["paper"], "reserved": true, "game_changer": false, "foil": true, "nonfoil": false, "finishes": ["foil"], "oversized": false, "promo": true, "reprint": true, "variation": false, "set_id": "5ba81c6d-2344-4760-bb13-b7276205e73e", "set": "p04", "set_name": "Magic Player Rewards 2004", "set_type": "promo", "set_uri": "https://api.scryfall.com/sets/5ba81c6d-2344-4760-bb13-b7276205e73e", "set_search_uri": "https://api.scryfall.com/cards/search?order=set&q=e%3Ap04&unique=prints", "scryfall_set_uri": "https://scryfall.com/sets/p04?utm_source=api", "rulings_uri": "https://api.scryfall.com/cards/2b77caf8-711b-4597-a5a5-dead81568e5b/rulings", "prints_search_uri": "https://api.scryfall.com/cards/search?order=released&q=oracleid%3Aca1144c2-49a3-49b4-9085-3094141769ea&unique=prints", "collector_number": "1", "digital": false, "rarity": "rare", "watermark": "dci", "card_back_id": "0aeebaf5-8c7d-4636-9e82-8c27447861f7", "artist": "Dan Frazier", "artist_ids": ["059bba56-5feb-42e4-8c2e-e2f1e6ba11f9"], "illustration_id": "fe4cf815-8b8b-4aaf-afb1-54992203bdcd", "border_color": "black", "frame": "2003", "full_art": false, "textless": false, "booster": false, "story_spotlight": false, "promo_types": ["playerrewards"], "edhrec_rank": 23543, "prices": {"usd": null, "usd_foil": "31.87", "usd_etched": null, "eur": null, "eur_foil": "39.05", "tix": null}, "related_uris": {"tcgplayer_infinite_articles": "https://partner.tcgplayer.com/c/4931599/1830156/21018?subId1=api&trafcat=tcgplayer.com%2Fsearch%2Farticles&u=https%3A%2F%2Fwww.tcgplayer.com%2Fsearch%2Farticles%3FproductLineName%3Dmagic%26q%3DPowder%2BKeg", "tcgplayer_infinite_decks": "https://partner.tcgplayer.com/c/4931599/1830156/21018?subId1=api&trafcat=tcgplayer.com%2Fsearch%2Fdecks&u=https%3A%2F%2Fwww.tcgplayer.com%2Fsearch%2Fdecks%3FproductLineName%3Dmagic%26q%3DPowder%2BKeg", "edhrec": "https://edhrec.com/route/?cc=Powder+Keg"}, "purchase_uris": {"tcgplayer": "https://partner.tcgplayer.com/c/4931599/1830156/21018?subId1=api&u=https%3A%2F%2Fwww.tcgplayer.com%2Fproduct%2F38328%3Fpage%3D1", "cardmarket": "https://www.cardmarket.com/en/Magic/Products?idProduct=17567&referrer=scryfall&utm_campaign=card_prices&utm_medium=text&utm_source=scryfall", "cardhoarder": "https://www.cardhoarder.com/cards?affiliate_id=scryfall&data%5Bsearch%5D=Powder+Keg&ref=card-profile&utm_campaign=affiliate&utm_medium=card&utm_source=scryfall"}}, {"object": "card", "id": "46b60d95-b9bc-40f8-b986-bfa8e3eb74f3", "oracle_id": "6a7a9dff-ff9e-4005-a17f-6ea0c11c1d5a", "multiverse_ids": [], "tcgplayer_id": 78633, "name": "Spirit", "lang": "en", "released_at": "2004-01-01", "uri": "https://api.scryfall.com/cards/46b60d95-b9bc-40f8-b986-bfa8e3eb74f3", "scryfall_uri": "https://scryfall.com/card/p04/6/spirit?utm_source=api", "layout": "token", "highres_image": true, "image_status": "highres_scan", "image_uris": {"small": "https://cards.scryfall.io/small/front/4/6/46b60d95-b9bc-40f8-b986-bfa8e3eb74f3.jpg?1561757037", "normal": "https://cards.scryfall.io/normal/front/4/6/46b60d95-b9bc-40f8-b986-bfa8e3eb74f3.jpg?1561757037", "large": "https://cards.scryfall.io/large/front/4/6/46b60d95-b9bc-40f8-b986-bfa8e3eb74f3.jpg?1561757037", "png": "https://cards.scryfall.io/png/front/4/6/46b60d95-b9bc-40f8-b986-bfa8e3eb74f3.png?1561757037", "art_crop": "https://cards.scryfall.io/art_crop/front/4/6/46b60d95-b9bc-40f8-b986-bfa8e3eb74f3.jpg?1561757037", "border_crop": "https://cards.scryfall.io/border_crop/front/4/6/46b60d95-b9bc-40f8-b986-bfa8e3eb74f3.jpg?1561757037"}, "mana_cost": "", "cmc": 0.0, "type_line": "Token Creature \u2014 Spirit", "oracle_text": "", "power": "1", "toughness": "1", "colors": [], "color_identity": [], "keywords": [], "all_parts": [{"object": "related_card", "id": "16fcc1a2-f8e0-4126-81ef-4481985cf0bf", "component": "combo_piece", "name": "One with the Kami", "type_line": "Enchantment \u2014 Aura", "uri": "https://api.scryfall.com/cards/16fcc1a2-f8e0-4126-81ef-4481985cf0bf"}, {"object": "related_card", "id": "9883e973-54c3-4bec-91d8-22f2829cdfa2", "component": "combo_piece", "name": "Sekki, Seasons' Guide", "type_line": "Legendary Creature \u2014 Spirit", "uri": "https://api.scryfall.com/cards/9883e973-54c3-4bec-91d8-22f2829cdfa2"}, {"object": "related_card", "id": "3d609e89-cbb0-4715-bfcc-d4cbf1c303f9", "component": "combo_piece", "name": "Release to Memory", "type_line": "Instant", "uri": "https://api.scryfall.com/cards/3d609e89-cbb0-4715-bfcc-d4cbf1c303f9"}, {"object": "related_card", "id": "c4e4866e-13a8-4130-9895-60e762b7efea", "component": "combo_piece", "name": "Spiritual Visit", "type_line": "Instant \u2014 Arcane", "uri": "https://api.scryfall.com/cards/c4e4866e-13a8-4130-9895-60e762b7efea"}, {"object": "related_card", "id": "0b79b30e-e7aa-490e-b130-de7533e6e13b", "component": "combo_piece", "name": "Searchlight Companion", "type_line": "Artifact Creature \u2014 Drone", "uri": "https://api.scryfall.com/cards/0b79b30e-e7aa-490e-b130-de7533e6e13b"}, {"object": "related_card", "id": "0ab91962-ebad-46f6-9f90-7477c224d93d", "component": "combo_piece", "name": "Go-Shintai of Shared Purpose", "type_line": "Legendary Enchantment Creature \u2014 Shrine", "uri": "https://api.scryfall.com/cards/0ab91962-ebad-46f6-9f90-7477c224d93d"}, {"object": "related_card", "id": "a40e9071-7b27-4070-bc3a-c095c2128953", "component": "combo_piece", "name": "Promise of Bunrei", "type_line": "Enchantment", "uri": "https://api.scryfall.com/cards/a40e9071-7b27-4070-bc3a-c095c2128953"}, {"object": "related_card", "id": "46b60d95-b9bc-40f8-b986-bfa8e3eb74f3", "component": "token", "name": "Spirit", "type_line": "Token Creature \u2014 Spirit", "uri": "https://api.scryfall.com/cards/46b60d95-b9bc-40f8-b986-bfa8e3eb74f3"}, {"object": "related_card", "id": "e752b762-38b7-463c-aa09-37fecfe71a53", "component": "combo_piece", "name": "Dripping-Tongue Zubera", "type_line": "Creature \u2014 Zubera Spirit", "uri": "https://api.scryfall.com/cards/e752b762-38b7-463c-aa09-37fecfe71a53"}, {"object": "related_card", "id": "81e1dbb8-3df8-4e7e-b74b-baab7d6f97c1", "component": "combo_piece", "name": "Baku Altar", "type_line": "Artifact", "uri": "https://api.scryfall.com/cards/81e1dbb8-3df8-4e7e-b74b-baab7d6f97c1"}, {"object": "related_card", "id": "4d83e837-fcd1-4833-9117-e6f1bb53caad", "component": "combo_piece", "name": "Akki Ember-Keeper", "type_line": "Enchantment Creature \u2014 Goblin Warrior", "uri": "https://api.scryfall.com/cards/4d83e837-fcd1-4833-9117-e6f1bb53caad"}, {"object": "related_card", "id": "003b8c93-54d2-4f23-961e-a52d63d0a54b", "component": "combo_piece", "name": "The Restoration of Eiganjo // Architect of Restoration", "type_line": "Enchantment \u2014 Saga // Enchantment Creature \u2014 Fox Monk", "uri": "https://api.scryfall.com/cards/003b8c93-54d2-4f23-961e-a52d63d0a54b"}, {"object": "related_card", "id": "84241b2e-fed0-4bf4-8a1c-4d1814c2eb8b", "component": "combo_piece", "name": "Honden of Life's Web", "type_line": "Legendary Enchantment \u2014 Shrine", "uri": "https://api.scryfall.com/cards/84241b2e-fed0-4bf4-8a1c-4d1814c2eb8b"}, {"object": "related_card", "id": "bdc33a21-d196-4c17-a296-87ff08e7ef69", "component": "combo_piece", "name": "Gods' Eye, Gate to the Reikai", "type_line": "Legendary Land", "uri": "https://api.scryfall.com/cards/bdc33a21-d196-4c17-a296-87ff08e7ef69"}, {"object": "related_card", "id": "c453026f-8a63-46f5-8b7a-720e0ec95858", "component": "combo_piece", "name": "Concord with the Kami", "type_line": "Enchantment", "uri": "https://api.scryfall.com/cards/c453026f-8a63-46f5-8b7a-720e0ec95858"}, {"object": "related_card", "id": "7ebf2cde-788d-4b38-8d24-fdb113943d0c", "component": "combo_piece", "name": "Myojin of Blooming Dawn", "type_line": "Legendary Creature \u2014 Spirit", "uri": "https://api.scryfall.com/cards/7ebf2cde-788d-4b38-8d24-fdb113943d0c"}, {"object": "related_card", "id": "e2b6a2df-35cc-4d4b-b50b-99ef33678346", "component": "combo_piece", "name": "Sokenzan, Crucible of Defiance", "type_line": "Legendary Land", "uri": "https://api.scryfall.com/cards/e2b6a2df-35cc-4d4b-b50b-99ef33678346"}, {"object": "related_card", "id": "8454624b-58bc-47c8-b0e6-6d4f0931a1ad", "component": "combo_piece", "name": "Teachings of the Kirin // Kirin-Touched Orochi", "type_line": "Enchantment \u2014 Saga // Enchantment Creature \u2014 Snake Monk", "uri": "https://api.scryfall.com/cards/8454624b-58bc-47c8-b0e6-6d4f0931a1ad"}, {"object": "related_card", "id": "3f79add5-6c23-4a36-86d3-8647605d2a71", "component": "combo_piece", "name": "Forbidden Orchard", "type_line": "Land", "uri": "https://api.scryfall.com/cards/3f79add5-6c23-4a36-86d3-8647605d2a71"}], "legalities": {"standard": "not_legal", "future": "not_legal", "historic": "not_legal", "timeless": "not_legal", "gladiator": "not_legal", "pioneer": "not_legal", "modern": "not_legal", "legacy": "not_legal", "pauper": "not_legal", "vintage": "not_legal", "penny": "not_legal", "commander": "not_legal", "oathbreaker": "not_legal", "standardbrawl": "not_legal", "brawl": "not_legal", "alchemy": "not_legal", "paupercommander": "not_legal", "duel": "not_legal", "oldschool": "not_legal", "premodern": "not_legal", "predh": "not_legal"}, "games": ["paper"], "reserved": false, "game_changer": false, "foil": false, "nonfoil": true, "finishes": ["nonfoil"], "oversized": false, "promo": true, "reprint": true, "variation": false, "set_id": "5ba81c6d-2344-4760-bb13-b7276205e73e", "set": "p04", "set_name": "Magic Player Rewards 2004", "set_type": "promo", "set_uri": "https://api.scryfall.com/sets/5ba81c6d-2344-4760-bb13-b7276205e73e", "set_search_uri": "https://api.scryfall.com/cards/search?order=set&q=e%3Ap04&unique=prints", "scryfall_set_uri": "https://scryfall.com/sets/p04?utm_source=api", "rulings_uri": "https://api.scryfall.com/cards/46b60d95-b9bc-40f8-b986-bfa8e3eb74f3/rulings", "prints_search_uri": "https://api.scryfall.com/cards/search?order=released&q=oracleid%3A6a7a9dff-ff9e-4005-a17f-6ea0c11c1d5a&unique=prints", "collector_number": "6", "digital": false, "rarity": "common", "card_back_id": "0aeebaf5-8c7d-4636-9e82-8c27447861f7", "artist": "Hugh Jamieson", "artist_ids": ["ae735af7-4895-45e0-aeb5-58c82343942e"], "illustration_id": "a24db34c-adab-42ae-865d-1df62e1bd221", "border_color": "black", "frame": "2003", "full_art": false, "textless": false, "booster": false, "story_spotlight": false, "promo_types": ["playerrewards"], "prices": {"usd": "18.74", "usd_foil": null, "usd_etched": null, "eur": null, "eur_foil": null, "tix": null}, "related_uris": {"tcgplayer_infinite_articles": "https://partner.tcgplayer.com/c/4931599/1830156/21018?subId1=api&trafcat=tcgplayer.com%2Fsearch%2Farticles&u=https%3A%2F%2Fwww.tcgplayer.com%2Fsearch%2Farticles%3FproductLineName%3Dmagic%26q%3DSpirit", "tcgplayer_infinite_decks": "https://partner.tcgplayer.com/c/4931599/1830156/21018?subId1=api&trafcat=tcgplayer.com%2Fsearch%2Fdecks&u=https%3A%2F%2Fwww.tcgplayer.com%2Fsearch%2Fdecks%3FproductLineName%3Dmagic%26q%3DSpirit", "edhrec": "https://edhrec.com/route/?cc=Spirit"}, "purchase_uris": {"tcgplayer": "https://partner.tcgplayer.com/c/4931599/1830156/21018?subId1=api&u=https%3A%2F%2Fwww.tcgplayer.com%2Fproduct%2F78633%3Fpage%3D1", "cardmarket": "https://www.cardmarket.com/en/Magic/Products/Search?referrer=scryfall&searchString=Spirit&utm_campaign=card_prices&utm_medium=text&utm_source=scryfall", "cardhoarder": "https://www.cardhoarder.com/cards?affiliate_id=scryfall&data%5Bsearch%5D=Spirit&ref=card-profile&utm_campaign=affiliate&utm_medium=card&utm_source=scryfall"}}, {"object": "card", "id": "4fbb0dc6-2f9e-4389-8a90-531e94009bfb", "oracle_id": "c9e57f97-be25-4ab6-9158-d2677d7742f7", "multiverse_ids": [], "tcgplayer_id": 78627, "name": "Pentavite", "lang": "en", "released_at": "2004-01-01", "uri": "https://api.scryfall.com/cards/4fbb0dc6-2f9e-4389-8a90-531e94009bfb", "scryfall_uri": "https://scryfall.com/card/p04/3/pentavite?utm_source=api", "layout": "token", "highres_image": true, "image_status": "highres_scan", "image_uris": {"small": "https://cards.scryfall.io/small/front/4/f/4fbb0dc6-2f9e-4389-8a90-531e94009bfb.jpg?1561757118", "normal": "https://cards.scryfall.io/normal/front/4/f/4fbb0dc6-2f9e-4389-8a90-531e94009bfb.jpg?1561757118", "large": "https://cards.scryfall.io/large/front/4/f/4fbb0dc6-2f9e-4389-8a90-531e94009bfb.jpg?1561757118", "png": "https://cards.scryfall.io/png/front/4/f/4fbb0dc6-2f9e-4389-8a90-531e94009bfb.png?1561757118", "art_crop": "https://cards.scryfall.io/art_crop/front/4/f/4fbb0dc6-2f9e-4389-8a90-531e94009bfb.jpg?1561757118", "border_crop": "https://cards.scryfall.io/border_crop/front/4/f/4fbb0dc6-2f9e-4389-8a90-531e94009bfb.jpg?1561757118"}, "mana_cost": "", "cmc": 0.0, "type_line": "Token Artifact Creature \u2014 Pentavite", "oracle_text": "Flying", "power": "1", "toughness": "1", "colors": [], "color_identity": [], "keywords": ["Flying"], "all_parts": [{"object": "related_card", "id": "a39ab7f7-c22f-4cf7-ae1f-d40b84996177", "component": "combo_piece", "name": "Pentavus", "type_line": "Artifact Creature \u2014 Construct", "uri": "https://api.scryfall.com/cards/a39ab7f7-c22f-4cf7-ae1f-d40b84996177"}, {"object": "related_card", "id": "4fbb0dc6-2f9e-4389-8a90-531e94009bfb", "component": "token", "name": "Pentavite", "type_line": "Token Artifact Creature \u2014 Pentavite", "uri": "https://api.scryfall.com/cards/4fbb0dc6-2f9e-4389-8a90-531e94009bfb"}], "legalities": {"standard": "not_legal", "future": "not_legal", "historic": "not_legal", "timeless": "not_legal", "gladiator": "not_legal", "pioneer": "not_legal", "modern": "not_legal", "legacy": "not_legal", "pauper": "not_legal", "vintage": "not_legal", "penny": "not_legal", "commander": "not_legal", "oathbreaker": "not_legal", "standardbrawl": "not_legal", "brawl": "not_legal", "alchemy": "not_legal", "paupercommander": "not_legal", "duel": "not_legal", "oldschool": "not_legal", "premodern": "not_legal", "predh": "not_legal"}, "games": ["paper"], "reserved": false, "game_changer": false, "foil": false, "nonfoil": true, "finishes": ["nonfoil"], "oversized": false, "promo": true, "reprint": true, "variation": false, "set_id": "5ba81c6d-2344-4760-bb13-b7276205e73e", "set": "p04", "set_name": "Magic Player Rewards 2004", "set_type": "promo", "set_uri": "https://api.scryfall.com/sets/5ba81c6d-2344-4760-bb13-b7276205e73e", "set_search_uri": "https://api.scryfall.com/cards/search?order=set&q=e%3Ap04&unique=prints", "scryfall_set_uri": "https://scryfall.com/sets/p04?utm_source=api", "rulings_uri": "https://api.scryfall.com/cards/4fbb0dc6-2f9e-4389-8a90-531e94009bfb/rulings", "prints_search_uri": "https://api.scryfall.com/cards/search?order=released&q=oracleid%3Ac9e57f97-be25-4ab6-9158-d2677d7742f7&unique=prints", "collector_number": "3", "digital": false, "rarity": "common", "card_back_id": "0aeebaf5-8c7d-4636-9e82-8c27447861f7", "artist": "Greg Staples", "artist_ids": ["93d65564-bf00-447b-8406-e2031f03b6b1"], "illustration_id": "27378cca-8d9e-433d-8994-f374bb87b3ed", "border_color": "black", "frame": "2003", "full_art": false, "textless": false, "booster": false, "story_spotlight": false, "promo_types": ["playerrewards"], "prices": {"usd": "0.77", "usd_foil": null, "usd_etched": null, "eur": null, "eur_foil": null, "tix": null}, "related_uris": {"tcgplayer_infinite_articles": "https://partner.tcgplayer.com/c/4931599/1830156/21018?subId1=api&trafcat=tcgplayer.com%2Fsearch%2Farticles&u=https%3A%2F%2Fwww.tcgplayer.com%2Fsearch%2Farticles%3FproductLineName%3Dmagic%26q%3DPentavite", "tcgplayer_infinite_decks": "https://partner.tcgplayer.com/c/4931599/1830156/21018?subId1=api&trafcat=tcgplayer.com%2Fsearch%2Fdecks&u=https%3A%2F%2Fwww.tcgplayer.com%2Fsearch%2Fdecks%3FproductLineName%3Dmagic%26q%3DPentavite", "edhrec": "https://edhrec.com/route/?cc=Pentavite"}, "purchase_uris": {"tcgplayer": "https://partner.tcgplayer.com/c/4931599/1830156/21018?subId1=api&u=https%3A%2F%2Fwww.tcgplayer.com%2Fproduct%2F78627%3Fpage%3D1", "cardmarket": "https://www.cardmarket.com/en/Magic/Products/Search?referrer=scryfall&searchString=Pentavite&utm_campaign=card_prices&utm_medium=text&utm_source=scryfall", "cardhoarder": "https://www.cardhoarder.com/cards?affiliate_id=scryfall&data%5Bsearch%5D=Pentavite&ref=card-profile&utm_campaign=affiliate&utm_medium=card&utm_source=scryfall"}}, {"object": "card", "id": "c7f3264a-7b4a-4fef-af73-d4241742a4e8", "oracle_id": "40c64f08-ab2f-4933-8e0e-d1a1c729008f", "multiverse_ids": [], "tcgplayer_id": 78613, "name": "Angel", "lang": "en", "released_at": "2004-01-01", "uri": "https://api.scryfall.com/cards/c7f3264a-7b4a-4fef-af73-d4241742a4e8", "scryfall_uri": "https://scryfall.com/card/p04/2/angel?utm_source=api", "layout": "token", "highres_image": true, "image_status": "highres_scan", "image_uris": {"small": "https://cards.scryfall.io/small/front/c/7/c7f3264a-7b4a-4fef-af73-d4241742a4e8.jpg?1561758046", "normal": "https://cards.scryfall.io/normal/front/c/7/c7f3264a-7b4a-4fef-af73-d4241742a4e8.jpg?1561758046", "large": "https://cards.scryfall.io/large/front/c/7/c7f3264a-7b4a-4fef-af73-d4241742a4e8.jpg?1561758046", "png": "https://cards.scryfall.io/png/front/c/7/c7f3264a-7b4a-4fef-af73-d4241742a4e8.png?1561758046", "art_crop": "https://cards.scryfall.io/art_crop/front/c/7/c7f3264a-7b4a-4fef-af73-d4241742a4e8.jpg?1561758046", "border_crop": "https://cards.scryfall.io/border_crop/front/c/7/c7f3264a-7b4a-4fef-af73-d4241742a4e8.jpg?1561758046"}, "mana_cost": "", "cmc": 0.0, "type_line": "Token Creature \u2014 Angel", "oracle_text": "Flying", "power": "4", "toughness": "4", "colors": ["W"], "color_identity": ["W"], "keywords": ["Flying"], "all_parts": [{"object": "related_card", "id": "17604107-8f0d-4b52-943e-7720638a362c", "component": "combo_piece", "name": "Empyrial Storm", "type_line": "Sorcery", "uri": "https://api.scryfall.com/cards/17604107-8f0d-4b52-943e-7720638a362c"}, {"object": "related_card", "id": "05d99dc7-1cc5-484a-ac72-12e77e80e41f", "component": "combo_piece", "name": "Seraphic Greatsword", "type_line": "Artifact \u2014 Equipment", "uri": "https://api.scryfall.com/cards/05d99dc7-1cc5-484a-ac72-12e77e80e41f"}, {"object": "related_card", "id": "69c77c6c-fa5e-429d-a41f-c33b032d9925", "component": "combo_piece", "name": "Angelic Favor", "type_line": "Instant", "uri": "https://api.scryfall.com/cards/69c77c6c-fa5e-429d-a41f-c33b032d9925"}, {"object": "related_card", "id": "c460abcf-43d8-4184-b654-3d247164aa3b", "component": "combo_piece", "name": "Saint Traft and Rem Karolus", "type_line": "Legendary Creature \u2014 Spirit Human", "uri": "https://api.scryfall.com/cards/c460abcf-43d8-4184-b654-3d247164aa3b"}, {"object": "related_card", "id": "6875be24-1515-488f-a899-929c8e480dfd", "component": "combo_piece", "name": "Sigil of the Empty Throne", "type_line": "Enchantment", "uri": "https://api.scryfall.com/cards/6875be24-1515-488f-a899-929c8e480dfd"}, {"object": "related_card", "id": "c7f3264a-7b4a-4fef-af73-d4241742a4e8", "component": "token", "name": "Angel", "type_line": "Token Creature \u2014 Angel", "uri": "https://api.scryfall.com/cards/c7f3264a-7b4a-4fef-af73-d4241742a4e8"}, {"object": "related_card", "id": "42eac2d9-3f41-47f9-a3ae-7cfdcd4c945c", "component": "combo_piece", "name": "Geist of Saint Traft", "type_line": "Legendary Creature \u2014 Spirit Cleric", "uri": "https://api.scryfall.com/cards/42eac2d9-3f41-47f9-a3ae-7cfdcd4c945c"}, {"object": "related_card", "id": "8771abc9-e1f2-4d4f-8492-3209866cdc05", "component": "combo_piece", "name": "Urbis Protector", "type_line": "Creature \u2014 Human Cleric", "uri": "https://api.scryfall.com/cards/8771abc9-e1f2-4d4f-8492-3209866cdc05"}, {"object": "related_card", "id": "e8cca776-b0e4-4cd2-815f-36c1f86cf497", "component": "combo_piece", "name": "Angelic Ascension", "type_line": "Instant", "uri": "https://api.scryfall.com/cards/e8cca776-b0e4-4cd2-815f-36c1f86cf497"}, {"object": "related_card", "id": "21637fbe-d9d3-4d5b-a361-0687385d4738", "component": "combo_piece", "name": "Decree of Justice", "type_line": "Sorcery", "uri": "https://api.scryfall.com/cards/21637fbe-d9d3-4d5b-a361-0687385d4738"}, {"object": "related_card", "id": "b3770d86-4496-4c06-aab1-2917cfec100e", "component": "combo_piece", "name": "Luminarch Ascension", "type_line": "Enchantment", "uri": "https://api.scryfall.com/cards/b3770d86-4496-4c06-aab1-2917cfec100e"}, {"object": "related_card", "id": "83245e11-a020-4d81-9d83-e1505f1d125e", "component": "combo_piece", "name": "Descend upon the Sinful", "type_line": "Sorcery", "uri": "https://api.scryfall.com/cards/83245e11-a020-4d81-9d83-e1505f1d125e"}, {"object": "related_card", "id": "b2cb986c-2a8e-4a24-b5d4-4393edc0c347", "component": "combo_piece", "name": "Angelic Accord", "type_line": "Enchantment", "uri": "https://api.scryfall.com/cards/b2cb986c-2a8e-4a24-b5d4-4393edc0c347"}, {"object": "related_card", "id": "ff4411bc-ed4e-4d54-9e1b-21fc77b0e415", "component": "combo_piece", "name": "Entreat the Angels", "type_line": "Sorcery", "uri": "https://api.scryfall.com/cards/ff4411bc-ed4e-4d54-9e1b-21fc77b0e415"}, {"object": "related_card", "id": "5efcbd08-708f-4a4d-ab1a-b0cb81f451e8", "component": "combo_piece", "name": "Invocation of Saint Traft", "type_line": "Enchantment \u2014 Aura", "uri": "https://api.scryfall.com/cards/5efcbd08-708f-4a4d-ab1a-b0cb81f451e8"}, {"object": "related_card", "id": "22422b00-d3c1-4668-8196-02678890ff75", "component": "combo_piece", "name": "Moonsilver Spear", "type_line": "Artifact \u2014 Equipment", "uri": "https://api.scryfall.com/cards/22422b00-d3c1-4668-8196-02678890ff75"}, {"object": "related_card", "id": "4a7c3dd3-a2e3-400a-8d2e-242bb8de39c1", "component": "combo_piece", "name": "Speaker of the Heavens", "type_line": "Creature \u2014 Human Cleric", "uri": "https://api.scryfall.com/cards/4a7c3dd3-a2e3-400a-8d2e-242bb8de39c1"}, {"object": "related_card", "id": "dc098d5b-0cdb-422f-8bd2-7afd81a7b7c3", "component": "combo_piece", "name": "Court of Grace", "type_line": "Enchantment", "uri": "https://api.scryfall.com/cards/dc098d5b-0cdb-422f-8bd2-7afd81a7b7c3"}, {"object": "related_card", "id": "8a286954-fb40-4440-9f0e-a28367c6823c", "component": "combo_piece", "name": "Devout Invocation", "type_line": "Sorcery", "uri": "https://api.scryfall.com/cards/8a286954-fb40-4440-9f0e-a28367c6823c"}], "legalities": {"standard": "not_legal", "future": "not_legal", "historic": "not_legal", "timeless": "not_legal", "gladiator": "not_legal", "pioneer": "not_legal", "modern": "not_legal", "legacy": "not_legal", "pauper": "not_legal", "vintage": "not_legal", "penny": "not_legal", "commander": "not_legal", "oathbreaker": "not_legal", "standardbrawl": "not_legal", "brawl": "not_legal", "alchemy": "not_legal", "paupercommander": "not_legal", "duel": "not_legal", "oldschool": "not_legal", "premodern": "not_legal", "predh": "not_legal"}, "games": ["paper"], "reserved": false, "game_changer": false, "foil": false, "nonfoil": true, "finishes": ["nonfoil"], "oversized": false, "promo": true, "reprint": true, "variation": false, "set_id": "5ba81c6d-2344-4760-bb13-b7276205e73e", "set": "p04", "set_name": "Magic Player Rewards 2004", "set_type": "promo", "set_uri": "https://api.scryfall.com/sets/5ba81c6d-2344-4760-bb13-b7276205e73e", "set_search_uri": "https://api.scryfall.com/cards/search?order=set&q=e%3Ap04&unique=prints", "scryfall_set_uri": "https://scryfall.com/sets/p04?utm_source=api", "rulings_uri": "https://api.scryfall.com/cards/c7f3264a-7b4a-4fef-af73-d4241742a4e8/rulings", "prints_search_uri": "https://api.scryfall.com/cards/search?order=released&q=oracleid%3A40c64f08-ab2f-4933-8e0e-d1a1c729008f&unique=prints", "collector_number": "2", "digital": false, "rarity": "common", "card_back_id": "0aeebaf5-8c7d-4636-9e82-8c27447861f7", "artist": "Scott M. Fischer", "artist_ids": ["23b0cf43-3e43-44c6-8329-96446eca5bce"], "illustration_id": "6c72b80e-6584-407a-9408-e655314c8642", "border_color": "black", "frame": "2003", "full_art": false, "textless": false, "booster": false, "story_spotlight": false, "promo_types": ["playerrewards"], "prices": {"usd": "13.30", "usd_foil": null, "usd_etched": null, "eur": null, "eur_foil": null, "tix": null}, "related_uris": {"tcgplayer_infinite_articles": "https://partner.tcgplayer.com/c/4931599/1830156/21018?subId1=api&trafcat=tcgplayer.com%2Fsearch%2Farticles&u=https%3A%2F%2Fwww.tcgplayer.com%2Fsearch%2Farticles%3FproductLineName%3Dmagic%26q%3DAngel", "tcgplayer_infinite_decks": "https://partner.tcgplayer.com/c/4931599/1830156/21018?subId1=api&trafcat=tcgplayer.com%2Fsearch%2Fdecks&u=https%3A%2F%2Fwww.tcgplayer.com%2Fsearch%2Fdecks%3FproductLineName%3Dmagic%26q%3DAngel", "edhrec": "https://edhrec.com/route/?cc=Angel"}, "purchase_uris": {"tcgplayer": "https://partner.tcgplayer.com/c/4931599/1830156/21018?subId1=api&u=https%3A%2F%2Fwww.tcgplayer.com%2Fproduct%2F78613%3Fpage%3D1", "cardmarket": "https://www.cardmarket.com/en/Magic/Products/Search?referrer=scryfall&searchString=Angel&utm_campaign=card_prices&utm_medium=text&utm_source=scryfall", "cardhoarder": "https://www.cardhoarder.com/cards?affiliate_id=scryfall&data%5Bsearch%5D=Angel&ref=card-profile&utm_campaign=affiliate&utm_medium=card&utm_source=scryfall"}}, {"object": "card", "id": "d02d5670-fff3-4011-8e45-e6843e4e8988", "oracle_id": "6bb61f34-5d57-4eaa-a02c-f5d08c1ee920", "multiverse_ids": [], "tcgplayer_id": 78616, "name": "Beast", "lang": "en", "released_at": "2004-01-01", "uri": "https://api.scryfall.com/cards/d02d5670-fff3-4011-8e45-e6843e4e8988", "scryfall_uri": "https://scryfall.com/card/p04/5/beast?utm_source=api", "layout": "token", "highres_image": true, "image_status": "highres_scan", "image_uris": {"small": "https://cards.scryfall.io/small/front/d/0/d02d5670-fff3-4011-8e45-e6843e4e8988.jpg?1561758119", "normal": "https://cards.scryfall.io/normal/front/d/0/d02d5670-fff3-4011-8e45-e6843e4e8988.jpg?1561758119", "large": "https://cards.scryfall.io/large/front/d/0/d02d5670-fff3-4011-8e45-e6843e4e8988.jpg?1561758119", "png": "https://cards.scryfall.io/png/front/d/0/d02d5670-fff3-4011-8e45-e6843e4e8988.png?1561758119", "art_crop": "https://cards.scryfall.io/art_crop/front/d/0/d02d5670-fff3-4011-8e45-e6843e4e8988.jpg?1561758119", "border_crop": "https://cards.scryfall.io/border_crop/front/d/0/d02d5670-fff3-4011-8e45-e6843e4e8988.jpg?1561758119"}, "mana_cost": "", "cmc": 0.0, "type_line": "Token Creature \u2014 Beast", "oracle_text": "", "power": "3", "toughness": "3", "colors": ["G"], "color_identity": ["G"], "keywords": [], "all_parts": [{"object": "related_card", "id": "19ca91ea-dffd-44a9-a54a-c664d83c357b", "component": "combo_piece", "name": "Druid of Horns", "type_line": "Creature \u2014 Human Druid", "uri": "https://api.scryfall.com/cards/19ca91ea-dffd-44a9-a54a-c664d83c357b"}, {"object": "related_card", "id": "beda7acd-e970-4222-9577-5133765d6052", "component": "combo_piece", "name": "Thragtusk", "type_line": "Creature \u2014 Beast", "uri": "https://api.scryfall.com/cards/beda7acd-e970-4222-9577-5133765d6052"}, {"object": "related_card", "id": "6b12a208-0ecf-4403-b988-d8c5ccc2906d", "component": "combo_piece", "name": "Garruk Wildspeaker", "type_line": "Legendary Planeswalker \u2014 Garruk", "uri": "https://api.scryfall.com/cards/6b12a208-0ecf-4403-b988-d8c5ccc2906d"}, {"object": "related_card", "id": "88cf1c67-9edc-42dd-ba7f-96baab25813a", "component": "combo_piece", "name": "Pulse of the Tangle", "type_line": "Sorcery", "uri": "https://api.scryfall.com/cards/88cf1c67-9edc-42dd-ba7f-96baab25813a"}, {"object": "related_card", "id": "79cfc0d7-fccb-47fb-87b6-08dd32528be6", "component": "combo_piece", "name": "Garruk, Primal Hunter", "type_line": "Legendary Planeswalker \u2014 Garruk", "uri": "https://api.scryfall.com/cards/79cfc0d7-fccb-47fb-87b6-08dd32528be6"}, {"object": "related_card", "id": "5ab07f63-f52f-47b8-8dd1-a1d6414b6ba2", "component": "combo_piece", "name": "Wild Endeavor", "type_line": "Sorcery", "uri": "https://api.scryfall.com/cards/5ab07f63-f52f-47b8-8dd1-a1d6414b6ba2"}, {"object": "related_card", "id": "d8c0c7e7-81f5-4e75-8120-95488fd6ff60", "component": "combo_piece", "name": "Feral Incarnation", "type_line": "Sorcery", "uri": "https://api.scryfall.com/cards/d8c0c7e7-81f5-4e75-8120-95488fd6ff60"}, {"object": "related_card", "id": "5c7ce150-5a57-47d4-a076-7249c36a2d78", "component": "combo_piece", "name": "Garruk, Unleashed", "type_line": "Legendary Planeswalker \u2014 Garruk", "uri": "https://api.scryfall.com/cards/5c7ce150-5a57-47d4-a076-7249c36a2d78"}, {"object": "related_card", "id": "e5729bd1-f480-4a9a-a36c-c36bf4b85a3f", "component": "combo_piece", "name": "Elder Gargaroth", "type_line": "Creature \u2014 Beast", "uri": "https://api.scryfall.com/cards/e5729bd1-f480-4a9a-a36c-c36bf4b85a3f"}, {"object": "related_card", "id": "78bbdc81-d47f-4f0a-b359-c146cc07931d", "component": "combo_piece", "name": "Fresh Meat", "type_line": "Instant", "uri": "https://api.scryfall.com/cards/78bbdc81-d47f-4f0a-b359-c146cc07931d"}, {"object": "related_card", "id": "265b59b4-e32f-4c73-b896-8fb1e88d8d52", "component": "combo_piece", "name": "Savage Conception", "type_line": "Sorcery", "uri": "https://api.scryfall.com/cards/265b59b4-e32f-4c73-b896-8fb1e88d8d52"}, {"object": "related_card", "id": "c7ea6b4f-36bb-4c84-a3cb-f962ece41b2b", "component": "combo_piece", "name": "Radagast, Wizard of Wilds", "type_line": "Legendary Creature \u2014 Avatar Wizard", "uri": "https://api.scryfall.com/cards/c7ea6b4f-36bb-4c84-a3cb-f962ece41b2b"}, {"object": "related_card", "id": "d02d5670-fff3-4011-8e45-e6843e4e8988", "component": "token", "name": "Beast", "type_line": "Token Creature \u2014 Beast", "uri": "https://api.scryfall.com/cards/d02d5670-fff3-4011-8e45-e6843e4e8988"}, {"object": "related_card", "id": "433e853d-bdd6-4151-ae17-97b0c05083f9", "component": "combo_piece", "name": "Vivien, Monsters' Advocate", "type_line": "Legendary Planeswalker \u2014 Vivien", "uri": "https://api.scryfall.com/cards/433e853d-bdd6-4151-ae17-97b0c05083f9"}, {"object": "related_card", "id": "3ca5c492-e7e8-48c3-ba98-db1ff50759bc", "component": "combo_piece", "name": "Trumpeting Gnarr", "type_line": "Creature \u2014 Beast", "uri": "https://api.scryfall.com/cards/3ca5c492-e7e8-48c3-ba98-db1ff50759bc"}, {"object": "related_card", "id": "7f419a04-7a18-4ea4-9581-bbc35bec4f16", "component": "combo_piece", "name": "Beast Within", "type_line": "Instant", "uri": "https://api.scryfall.com/cards/7f419a04-7a18-4ea4-9581-bbc35bec4f16"}, {"object": "related_card", "id": "a34a1550-183a-4f7d-ba28-f3249e13a9d6", "component": "combo_piece", "name": "Sawtusk Demolisher", "type_line": "Creature \u2014 Beast", "uri": "https://api.scryfall.com/cards/a34a1550-183a-4f7d-ba28-f3249e13a9d6"}, {"object": "related_card", "id": "e3563033-b1a9-402b-b289-4845efb17bfe", "component": "combo_piece", "name": "Soul of Zendikar", "type_line": "Creature \u2014 Avatar", "uri": "https://api.scryfall.com/cards/e3563033-b1a9-402b-b289-4845efb17bfe"}, {"object": "related_card", "id": "f2c2f50e-ccfd-494e-ac52-fc4846f1f4ea", "component": "combo_piece", "name": "The Huntsman's Redemption", "type_line": "Enchantment \u2014 Saga", "uri": "https://api.scryfall.com/cards/f2c2f50e-ccfd-494e-ac52-fc4846f1f4ea"}, {"object": "related_card", "id": "b40a7f65-10fe-4ce5-ad1c-be53a635d7a9", "component": "combo_piece", "name": "Midsummer Revel", "type_line": "Enchantment", "uri": "https://api.scryfall.com/cards/b40a7f65-10fe-4ce5-ad1c-be53a635d7a9"}, {"object": "related_card", "id": "167eac91-56a8-4bfe-ac95-bb460e0206fa", "component": "combo_piece", "name": "Somberwald Beastmaster", "type_line": "Creature \u2014 Human Ranger", "uri": "https://api.scryfall.com/cards/167eac91-56a8-4bfe-ac95-bb460e0206fa"}, {"object": "related_card", "id": "4ab96b42-4240-4a24-bf58-c035ca8ec66b", "component": "combo_piece", "name": "Herd Migration", "type_line": "Sorcery", "uri": "https://api.scryfall.com/cards/4ab96b42-4240-4a24-bf58-c035ca8ec66b"}, {"object": "related_card", "id": "5a20acbc-6ca8-4b0c-ab7e-4bb8d429336b", "component": "combo_piece", "name": "Curious Herd", "type_line": "Instant", "uri": "https://api.scryfall.com/cards/5a20acbc-6ca8-4b0c-ab7e-4bb8d429336b"}, {"object": "related_card", "id": "3041bd1d-86cd-4c7c-b6d7-a33a7ae202fb", "component": "combo_piece", "name": "Bringer of the Green Dawn", "type_line": "Creature \u2014 Bringer", "uri": "https://api.scryfall.com/cards/3041bd1d-86cd-4c7c-b6d7-a33a7ae202fb"}, {"object": "related_card", "id": "f1623228-0935-4a8d-863c-249d613bd3ab", "component": "combo_piece", "name": "Primeval Bounty", "type_line": "Enchantment", "uri": "https://api.scryfall.com/cards/f1623228-0935-4a8d-863c-249d613bd3ab"}], "legalities": {"standard": "not_legal", "future": "not_legal", "historic": "not_legal", "timeless": "not_legal", "gladiator": "not_legal", "pioneer": "not_legal", "modern": "not_legal", "legacy": "not_legal", "pauper": "not_legal", "vintage": "not_legal", "penny": "not_legal", "commander": "not_legal", "oathbreaker": "not_legal", "standardbrawl": "not_legal", "brawl": "not_legal", "alchemy": "not_legal", "paupercommander": "not_legal", "duel": "not_legal", "oldschool": "not_legal", "premodern": "not_legal", "predh": "not_legal"}, "games": ["paper"], "reserved": false, "game_changer": false, "foil": false, "nonfoil": true, "finishes": ["nonfoil"], "oversized": false, "promo": true, "reprint": true, "variation": false, "set_id": "5ba81c6d-2344-4760-bb13-b7276205e73e", "set": "p04", "set_name": "Magic Player Rewards 2004", "set_type": "promo", "set_uri": "https://api.scryfall.com/sets/5ba81c6d-2344-4760-bb13-b7276205e73e", "set_search_uri": "https://api.scryfall.com/cards/search?order=set&q=e%3Ap04&unique=prints", "scryfall_set_uri": "https://scryfall.com/sets/p04?utm_source=api", "rulings_uri": "https://api.scryfall.com/cards/d02d5670-fff3-4011-8e45-e6843e4e8988/rulings", "prints_search_uri": "https://api.scryfall.com/cards/search?order=released&q=oracleid%3A6bb61f34-5d57-4eaa-a02c-f5d08c1ee920&unique=prints", "collector_number": "5", "digital": false, "rarity": "common", "card_back_id": "0aeebaf5-8c7d-4636-9e82-8c27447861f7", "artist": "Edward P. Beard, Jr.", "artist_ids": ["b845b8ee-aeea-4822-bcf9-7230625ac95c"], "illustration_id": "d2970c33-7006-4c2a-95fb-ec3c3dbe8ca1", "border_color": "black", "frame": "2003", "full_art": false, "textless": false, "booster": false, "story_spotlight": false, "promo_types": ["playerrewards"], "prices": {"usd": "5.91", "usd_foil": null, "usd_etched": null, "eur": null, "eur_foil": null, "tix": null}, "related_uris": {"tcgplayer_infinite_articles": "https://partner.tcgplayer.com/c/4931599/1830156/21018?subId1=api&trafcat=tcgplayer.com%2Fsearch%2Farticles&u=https%3A%2F%2Fwww.tcgplayer.com%2Fsearch%2Farticles%3FproductLineName%3Dmagic%26q%3DBeast", "tcgplayer_infinite_decks": "https://partner.tcgplayer.com/c/4931599/1830156/21018?subId1=api&trafcat=tcgplayer.com%2Fsearch%2Fdecks&u=https%3A%2F%2Fwww.tcgplayer.com%2Fsearch%2Fdecks%3FproductLineName%3Dmagic%26q%3DBeast", "edhrec": "https://edhrec.com/route/?cc=Beast"}, "purchase_uris": {"tcgplayer": "https://partner.tcgplayer.com/c/4931599/1830156/21018?subId1=api&u=https%3A%2F%2Fwww.tcgplayer.com%2Fproduct%2F78616%3Fpage%3D1", "cardmarket": "https://www.cardmarket.com/en/Magic/Products/Search?referrer=scryfall&searchString=Beast&utm_campaign=card_prices&utm_medium=text&utm_source=scryfall", "cardhoarder": "https://www.cardhoarder.com/cards?affiliate_id=scryfall&data%5Bsearch%5D=Beast&ref=card-profile&utm_campaign=affiliate&utm_medium=card&utm_source=scryfall"}}]